yuezhlib/__init__.py
yuezhlib/cantonese_tokenizer.py
yuezhlib-0.1.1.dist-info/METADATA
yuezhlib-0.1.1.dist-info/WHEEL
yuezhlib-0.1.1.dist-info/top_level.txt
yuezhlib-0.1.1.dist-info/RECORD
