Metadata-Version: 2.1
Name: yuezhlib
Version: 0.1.1
Summary: Library for preprocessing Cantonese and Written Chinese
Home-page: https://github.com/shivanraptor/yuezhlib
Author: Raptor K
Author-email: findme@raptor.hk
License: UNKNOWN
Keywords: Cantonese,preprocess
Platform: UNKNOWN
Classifier: Development Status :: 4 - Beta
Classifier: Intended Audience :: Developers
Classifier: Programming Language :: Python :: 3
Classifier: Operating System :: MacOS :: MacOS X
Classifier: Operating System :: Microsoft :: Windows
Classifier: License :: OSI Approved :: MIT License
Requires-Python: >=3.9.7
Requires-Dist: pycantonese
Requires-Dist: tokenizers
Requires-Dist: transformers
